{"data":{"team1":[{"id":"2797492","playerId":"162545","cardId":"200404","level":"100","exp":"1157454","breakLevel":"3","vigour":"100","skill":{"10807":{"level":34},"10808":{"level":34},"90404":{"level":1}},"businessSkill":[],"favorability":"2650","favorabilityLevel":"6","createTime":"2024-03-23 01:33:36","cardName":null,"defaultSkinId":"254040","marryTime":"1713707202","isArtifactUnlock":"1","lunaTowerHp":"1.0000","lunaTowerEnergy":"0.0000","pets":{"1":{"petId":"210070","level":"30","breakLevel":"14","character":"3","attr":[{"type":"3","num":"595","quality":"5"},{"type":"3","num":"595","quality":"5"},{"type":"3","num":"595","quality":"5"},{"type":"3","num":"595","quality":"5"}],"isEvolution":"1","playerPetId":"10763762"}},"artifactTalent":{"8":{"id":"77655","playerId":"162545","playerCardId":"2797492","talentId":"8","level":"3","type":"1","fragmentNum":"87","gemstoneId":null,"createTime":"2024-03-26 14:54:13"},"1":{"id":"77648","playerId":"162545","playerCardId":"2797492","talentId":"1","level":"2","type":"1","fragmentNum":"21","gemstoneId":null,"createTime":"2024-03-26 14:53:54"},"11":{"id":"77658","playerId":"162545","playerCardId":"2797492","talentId":"11","level":"3","type":"1","fragmentNum":"120","gemstoneId":null,"createTime":"2024-03-26 14:54:38"},"5":{"id":"77652","playerId":"162545","playerCardId":"2797492","talentId":"5","level":"2","type":"1","fragmentNum":"42","gemstoneId":null,"createTime":"2024-03-26 14:54:06"},"16":{"id":"77661","playerId":"162545","playerCardId":"2797492","talentId":"16","level":"4","type":"1","fragmentNum":"216","gemstoneId":null,"createTime":"2024-03-26 14:54:46"},"6":{"id":"77653","playerId":"162545","playerCardId":"2797492","talentId":"6","level":"1","type":"2","fragmentNum":"100","gemstoneId":"282106","createTime":"2024-03-26 14:54:08"},"15":{"id":"77660","playerId":"162545","playerCardId":"2797492","talentId":"15","level":"4","type":"1","fragmentNum":"186","gemstoneId":null,"createTime":"2024-03-26 14:54:44"},"14":{"id":"77659","playerId":"162545","playerCardId":"2797492","talentId":"14","level":"1","type":"2","fragmentNum":"400","gemstoneId":"284207","createTime":"2024-03-26 14:54:41"},"10":{"id":"77657","playerId":"162545","playerCardId":"2797492","talentId":"10","level":"3","type":"1","fragmentNum":"105","gemstoneId":null,"createTime":"2024-03-26 14:54:34"},"18":{"id":"77665","playerId":"162545","playerCardId":"2797492","talentId":"18","level":"1","type":"2","fragmentNum":"800","gemstoneId":"283107","createTime":"2024-03-26 22:03:30"},"4":{"id":"77651","playerId":"162545","playerCardId":"2797492","talentId":"4","level":"2","type":"1","fragmentNum":"36","gemstoneId":null,"createTime":"2024-03-26 14:54:04"},"2":{"id":"77649","playerId":"162545","playerCardId":"2797492","talentId":"2","level":"2","type":"1","fragmentNum":"27","gemstoneId":null,"createTime":"2024-03-26 14:53:56"},"9":{"id":"77656","playerId":"162545","playerCardId":"2797492","talentId":"9","level":"1","type":"2","fragmentNum":"200","gemstoneId":"280206","createTime":"2024-03-26 14:54:17"},"7":{"id":"77654","playerId":"162545","playerCardId":"2797492","talentId":"7","level":"2","type":"1","fragmentNum":"51","gemstoneId":null,"createTime":"2024-03-26 14:54:11"},"3":{"id":"77650","playerId":"162545","playerCardId":"2797492","talentId":"3","level":"1","type":"2","fragmentNum":"50","gemstoneId":"283006","createTime":"2024-03-26 14:53:59"},"17":{"id":"77662","playerId":"162545","playerCardId":"2797492","talentId":"17","level":"4","type":"1","fragmentNum":"243","gemstoneId":null,"createTime":"2024-03-26 17:05:32"}},"bookLevel":[],"equippedHouseCatGene":[],"playerPetId":"10763762","hp":27767,"attack":2222,"defence":331,"critRate":11075,"critDamage":11514,"attackRate":9644},{"id":"2213840","playerId":"162545","cardId":"200159","level":"120","exp":"2117198","breakLevel":"5","vigour":"100","skill":{"10317":{"level":41},"10318":{"level":41},"90159":{"level":1}},"businessSkill":[],"favorability":"2650","favorabilityLevel":"6","createTime":"2020-08-28 00:37:21","cardName":null,"defaultSkinId":"251591","marryTime":"1603300520","isArtifactUnlock":"1","lunaTowerHp":"1.0000","lunaTowerEnergy":"0.0000","pets":{"1":{"petId":"210060","level":"30","breakLevel":"15","character":"6","attr":[{"type":"6","num":"600","quality":"5"},{"type":"6","num":"600","quality":"5"},{"type":"6","num":"600","quality":"5"},{"type":"6","num":"600","quality":"5"}],"isEvolution":"1","playerPetId":"285980"}},"artifactTalent":{"8":{"id":"38564","playerId":"162545","playerCardId":"2213840","talentId":"8","level":"3","type":"1","fragmentNum":"87","gemstoneId":null,"createTime":"2020-09-04 00:19:41"},"1":{"id":"38557","playerId":"162545","playerCardId":"2213840","talentId":"1","level":"2","type":"1","fragmentNum":"21","gemstoneId":null,"createTime":"2020-09-04 00:19:19"},"11":{"id":"39337","playerId":"162545","playerCardId":"2213840","talentId":"11","level":"3","type":"1","fragmentNum":"120","gemstoneId":null,"createTime":"2020-09-05 16:02:39"},"5":{"id":"38561","playerId":"162545","playerCardId":"2213840","talentId":"5","level":"2","type":"1","fragmentNum":"42","gemstoneId":null,"createTime":"2020-09-04 00:19:31"},"16":{"id":"39340","playerId":"162545","playerCardId":"2213840","talentId":"16","level":"4","type":"1","fragmentNum":"216","gemstoneId":null,"createTime":"2020-09-05 16:02:53"},"6":{"id":"38562","playerId":"162545","playerCardId":"2213840","talentId":"6","level":"1","type":"2","fragmentNum":"100","gemstoneId":"282206","createTime":"2020-09-04 00:19:34"},"15":{"id":"39339","playerId":"162545","playerCardId":"2213840","talentId":"15","level":"4","type":"1","fragmentNum":"186","gemstoneId":null,"createTime":"2020-09-05 16:02:46"},"14":{"id":"39338","playerId":"162545","playerCardId":"2213840","talentId":"14","level":"1","type":"2","fragmentNum":"400","gemstoneId":"284206","createTime":"2020-09-05 16:02:43"},"10":{"id":"39101","playerId":"162545","playerCardId":"2213840","talentId":"10","level":"3","type":"1","fragmentNum":"105","gemstoneId":null,"createTime":"2020-09-04 16:13:19"},"18":{"id":"39681","playerId":"162545","playerCardId":"2213840","talentId":"18","level":"1","type":"2","fragmentNum":"800","gemstoneId":"283206","createTime":"2020-09-07 22:14:18"},"4":{"id":"38560","playerId":"162545","playerCardId":"2213840","talentId":"4","level":"2","type":"1","fragmentNum":"36","gemstoneId":null,"createTime":"2020-09-04 00:19:28"},"2":{"id":"38558","playerId":"162545","playerCardId":"2213840","talentId":"2","level":"2","type":"1","fragmentNum":"27","gemstoneId":null,"createTime":"2020-09-04 00:19:22"},"9":{"id":"38677","playerId":"162545","playerCardId":"2213840","talentId":"9","level":"1","type":"2","fragmentNum":"200","gemstoneId":"280204","createTime":"2020-09-04 01:13:25"},"7":{"id":"38563","playerId":"162545","playerCardId":"2213840","talentId":"7","level":"2","type":"1","fragmentNum":"51","gemstoneId":null,"createTime":"2020-09-04 00:19:38"},"3":{"id":"38559","playerId":"162545","playerCardId":"2213840","talentId":"3","level":"1","type":"2","fragmentNum":"50","gemstoneId":"283006","createTime":"2020-09-04 00:19:25"},"17":{"id":"39524","playerId":"162545","playerCardId":"2213840","talentId":"17","level":"4","type":"1","fragmentNum":"243","gemstoneId":null,"createTime":"2020-09-06 22:42:49"}},"bookLevel":[],"equippedHouseCatGene":[],"playerPetId":"285980","attackRate":32704,"attack":3622,"defence":813,"hp":12982,"critRate":14816,"critDamage":9542},{"id":"2293617","playerId":"162545","cardId":"200211","level":"120","exp":"2117198","breakLevel":"5","vigour":"100","skill":{"10421":{"level":41},"10422":{"level":41}},"businessSkill":[],"favorability":"2650","favorabilityLevel":"6","createTime":"2021-01-01 02:17:50","cardName":null,"defaultSkinId":"252110","marryTime":"1611526380","isArtifactUnlock":"1","lunaTowerHp":"1.0000","lunaTowerEnergy":"0.0000","pets":{"1":{"petId":"210060","level":"30","breakLevel":"14","character":"6","attr":[{"type":"6","num":"600","quality":"5"},{"type":"6","num":"600","quality":"5"},{"type":"6","num":"600","quality":"5"},{"type":"6","num":"600","quality":"5"}],"isEvolution":"1","playerPetId":"8702427"}},"artifactTalent":{"8":{"id":"44175","playerId":"162545","playerCardId":"2293617","talentId":"8","level":"3","type":"1","fragmentNum":"87","gemstoneId":null,"createTime":"2021-01-03 05:58:52"},"1":{"id":"44168","playerId":"162545","playerCardId":"2293617","talentId":"1","level":"2","type":"1","fragmentNum":"21","gemstoneId":null,"createTime":"2021-01-03 05:58:31"},"11":{"id":"44428","playerId":"162545","playerCardId":"2293617","talentId":"11","level":"3","type":"1","fragmentNum":"120","gemstoneId":null,"createTime":"2021-01-04 18:01:31"},"5":{"id":"44172","playerId":"162545","playerCardId":"2293617","talentId":"5","level":"2","type":"1","fragmentNum":"42","gemstoneId":null,"createTime":"2021-01-03 05:58:43"},"16":{"id":"44542","playerId":"162545","playerCardId":"2293617","talentId":"16","level":"4","type":"1","fragmentNum":"216","gemstoneId":null,"createTime":"2021-01-05 21:24:37"},"6":{"id":"44173","playerId":"162545","playerCardId":"2293617","talentId":"6","level":"1","type":"2","fragmentNum":"100","gemstoneId":"282206","createTime":"2021-01-03 05:58:45"},"15":{"id":"44531","playerId":"162545","playerCardId":"2293617","talentId":"15","level":"4","type":"1","fragmentNum":"186","gemstoneId":null,"createTime":"2021-01-05 20:18:58"},"14":{"id":"44530","playerId":"162545","playerCardId":"2293617","talentId":"14","level":"1","type":"2","fragmentNum":"400","gemstoneId":"284006","createTime":"2021-01-05 20:18:54"},"10":{"id":"44325","playerId":"162545","playerCardId":"2293617","talentId":"10","level":"3","type":"1","fragmentNum":"105","gemstoneId":null,"createTime":"2021-01-03 20:09:24"},"18":{"id":"44683","playerId":"162545","playerCardId":"2293617","talentId":"18","level":"1","type":"2","fragmentNum":"800","gemstoneId":"283005","createTime":"2021-01-06 22:53:58"},"4":{"id":"44171","playerId":"162545","playerCardId":"2293617","talentId":"4","level":"2","type":"1","fragmentNum":"36","gemstoneId":null,"createTime":"2021-01-03 05:58:40"},"2":{"id":"44169","playerId":"162545","playerCardId":"2293617","talentId":"2","level":"2","type":"1","fragmentNum":"27","gemstoneId":null,"createTime":"2021-01-03 05:58:34"},"9":{"id":"44176","playerId":"162545","playerCardId":"2293617","talentId":"9","level":"1","type":"2","fragmentNum":"200","gemstoneId":"280106","createTime":"2021-01-03 05:58:58"},"7":{"id":"44174","playerId":"162545","playerCardId":"2293617","talentId":"7","level":"2","type":"1","fragmentNum":"51","gemstoneId":null,"createTime":"2021-01-03 05:58:50"},"3":{"id":"44170","playerId":"162545","playerCardId":"2293617","talentId":"3","level":"1","type":"2","fragmentNum":"50","gemstoneId":"283205","createTime":"2021-01-03 05:58:38"},"17":{"id":"44561","playerId":"162545","playerCardId":"2293617","talentId":"17","level":"4","type":"1","fragmentNum":"243","gemstoneId":null,"createTime":"2021-01-06 01:19:29"}},"bookLevel":[],"equippedHouseCatGene":[],"playerPetId":"8702427","attackRate":30976,"attack":4789,"defence":720,"hp":12492,"critRate":16600,"critDamage":14965},{"id":"2749695","playerId":"162545","cardId":"200375","level":"120","exp":"2096300","breakLevel":"5","vigour":"100","skill":{"10749":{"level":41},"10750":{"level":41},"90375":{"level":1}},"businessSkill":[],"favorability":"2650","favorabilityLevel":"6","createTime":"2023-09-17 17:33:02","cardName":null,"defaultSkinId":"253750","marryTime":"1700933355","isArtifactUnlock":"1","lunaTowerHp":"1.0000","lunaTowerEnergy":"0.0000","pets":{"1":{"petId":"210060","level":"30","breakLevel":"17","character":"6","attr":[{"type":"6","num":"600","quality":"5"},{"type":"6","num":"600","quality":"5"},{"type":"6","num":"600","quality":"5"},{"type":"1","num":"70","quality":"5"}],"isEvolution":"1","playerPetId":"7622958"}},"artifactTalent":{"8":{"id":"73535","playerId":"162545","playerCardId":"2749695","talentId":"8","level":"3","type":"1","fragmentNum":"87","gemstoneId":null,"createTime":"2023-09-27 00:17:11"},"1":{"id":"73528","playerId":"162545","playerCardId":"2749695","talentId":"1","level":"2","type":"1","fragmentNum":"21","gemstoneId":null,"createTime":"2023-09-27 00:16:31"},"5":{"id":"73532","playerId":"162545","playerCardId":"2749695","talentId":"5","level":"2","type":"1","fragmentNum":"42","gemstoneId":null,"createTime":"2023-09-27 00:17:02"},"16":{"id":"73655","playerId":"162545","playerCardId":"2749695","talentId":"16","level":"4","type":"1","fragmentNum":"216","gemstoneId":null,"createTime":"2023-09-27 06:44:03"},"12":{"id":"73537","playerId":"162545","playerCardId":"2749695","talentId":"12","level":"3","type":"1","fragmentNum":"105","gemstoneId":null,"createTime":"2023-09-27 00:17:34"},"6":{"id":"73533","playerId":"162545","playerCardId":"2749695","talentId":"6","level":"1","type":"2","fragmentNum":"100","gemstoneId":"282107","createTime":"2023-09-27 00:17:05"},"15":{"id":"73551","playerId":"162545","playerCardId":"2749695","talentId":"15","level":"4","type":"1","fragmentNum":"186","gemstoneId":null,"createTime":"2023-09-27 00:33:15"},"14":{"id":"73550","playerId":"162545","playerCardId":"2749695","talentId":"14","level":"1","type":"2","fragmentNum":"400","gemstoneId":"284107","createTime":"2023-09-27 00:33:12"},"13":{"id":"73538","playerId":"162545","playerCardId":"2749695","talentId":"13","level":"3","type":"1","fragmentNum":"120","gemstoneId":null,"createTime":"2023-09-27 00:17:45"},"18":{"id":"73766","playerId":"162545","playerCardId":"2749695","talentId":"18","level":"1","type":"2","fragmentNum":"800","gemstoneId":"281107","createTime":"2023-09-29 00:57:46"},"4":{"id":"73531","playerId":"162545","playerCardId":"2749695","talentId":"4","level":"2","type":"1","fragmentNum":"36","gemstoneId":null,"createTime":"2023-09-27 00:16:52"},"2":{"id":"73529","playerId":"162545","playerCardId":"2749695","talentId":"2","level":"2","type":"1","fragmentNum":"27","gemstoneId":null,"createTime":"2023-09-27 00:16:45"},"9":{"id":"73536","playerId":"162545","playerCardId":"2749695","talentId":"9","level":"1","type":"2","fragmentNum":"200","gemstoneId":"280207","createTime":"2023-09-27 00:17:14"},"7":{"id":"73534","playerId":"162545","playerCardId":"2749695","talentId":"7","level":"2","type":"1","fragmentNum":"51","gemstoneId":null,"createTime":"2023-09-27 00:17:08"},"3":{"id":"73530","playerId":"162545","playerCardId":"2749695","talentId":"3","level":"1","type":"2","fragmentNum":"50","gemstoneId":"281007","createTime":"2023-09-27 00:16:48"},"17":{"id":"73763","playerId":"162545","playerCardId":"2749695","talentId":"17","level":"4","type":"1","fragmentNum":"243","gemstoneId":null,"createTime":"2023-09-29 00:55:52"}},"bookLevel":[],"equippedHouseCatGene":[],"playerPetId":"7622958","attackRate":27888,"attack":4913,"defence":1607,"hp":14180,"critRate":10634,"critDamage":16469},{"id":"2812396","playerId":"162545","cardId":"200411","level":"110","exp":"1539150","breakLevel":"4","vigour":"100","skill":{"10821":{"level":37},"10822":{"level":37},"90411":{"level":1}},"businessSkill":[],"favorability":570,"favorabilityLevel":3,"createTime":"2024-06-07 01:08:10","cardName":null,"defaultSkinId":"254110","marryTime":null,"isArtifactUnlock":"1","lunaTowerHp":"1.0000","lunaTowerEnergy":"0.0000","pets":{"1":{"petId":"210060","level":"30","breakLevel":"10","character":"1","attr":[{"type":"1","num":"70","quality":"5"},{"type":"6","num":"600","quality":"5"},{"type":"6","num":"600","quality":"5"},{"type":"1","num":"70","quality":"5"}],"isEvolution":"1","playerPetId":"16629930"}},"artifactTalent":{"3":{"id":"79920","playerId":"162545","playerCardId":"2812396","talentId":"3","level":"1","type":"2","fragmentNum":"50","gemstoneId":"283205","createTime":"2024-08-23 14:52:28"},"2":{"id":"79919","playerId":"162545","playerCardId":"2812396","talentId":"2","level":"2","type":"1","fragmentNum":"27","gemstoneId":null,"createTime":"2024-08-23 14:52:10"},"1":{"id":"79918","playerId":"162545","playerCardId":"2812396","talentId":"1","level":"2","type":"1","fragmentNum":"21","gemstoneId":null,"createTime":"2024-08-23 14:50:39"}},"bookLevel":[],"equippedHouseCatGene":[],"playerPetId":"16629930","attack":3696,"attackRate":9344,"defence":366,"hp":8271,"critRate":5181,"critDamage":4615}],"team2":[{"id":"2326405","playerId":"162545","cardId":"200165","level":"120","exp":"2117198","breakLevel":"5","vigour":"100","skill":{"10329":{"level":41},"10330":{"level":41},"90165":{"level":1}},"businessSkill":[],"favorability":"2650","favorabilityLevel":"6","createTime":"2021-02-16 21:41:13","cardName":null,"defaultSkinId":"251651","marryTime":"1639598023","isArtifactUnlock":"1","lunaTowerHp":"1.0000","lunaTowerEnergy":"0.0000","pets":{"1":{"petId":"210025","level":"30","breakLevel":"14","character":"1","attr":[{"type":"3","num":"595","quality":"5"},{"type":"1","num":"60","quality":"5"},{"type":"1","num":"60","quality":"5"},{"type":"1","num":"60","quality":"5"}],"isEvolution":"1","playerPetId":"4535414"}},"artifactTalent":{"8":{"id":"56217","playerId":"162545","playerCardId":"2326405","talentId":"8","level":"3","type":"1","fragmentNum":"87","gemstoneId":null,"createTime":"2021-11-12 01:06:25"},"1":{"id":"55989","playerId":"162545","playerCardId":"2326405","talentId":"1","level":"2","type":"1","fragmentNum":"21","gemstoneId":null,"createTime":"2021-11-08 19:51:13"},"11":{"id":"56220","playerId":"162545","playerCardId":"2326405","talentId":"11","level":"3","type":"1","fragmentNum":"120","gemstoneId":null,"createTime":"2021-11-12 01:06:50"},"5":{"id":"56214","playerId":"162545","playerCardId":"2326405","talentId":"5","level":"2","type":"1","fragmentNum":"42","gemstoneId":null,"createTime":"2021-11-12 01:06:09"},"16":{"id":"56450","playerId":"162545","playerCardId":"2326405","talentId":"16","level":"4","type":"1","fragmentNum":"216","gemstoneId":null,"createTime":"2021-11-13 17:10:32"},"6":{"id":"56215","playerId":"162545","playerCardId":"2326405","talentId":"6","level":"1","type":"2","fragmentNum":"100","gemstoneId":null,"createTime":"2021-11-12 01:06:14"},"15":{"id":"56226","playerId":"162545","playerCardId":"2326405","talentId":"15","level":"4","type":"1","fragmentNum":"186","gemstoneId":null,"createTime":"2021-11-12 01:09:41"},"14":{"id":"56221","playerId":"162545","playerCardId":"2326405","talentId":"14","level":"1","type":"2","fragmentNum":"400","gemstoneId":"284007","createTime":"2021-11-12 01:07:28"},"10":{"id":"56219","playerId":"162545","playerCardId":"2326405","talentId":"10","level":"3","type":"1","fragmentNum":"105","gemstoneId":null,"createTime":"2021-11-12 01:06:47"},"18":{"id":"56541","playerId":"162545","playerCardId":"2326405","talentId":"18","level":"1","type":"2","fragmentNum":"800","gemstoneId":"285207","createTime":"2021-11-14 18:01:43"},"4":{"id":"56213","playerId":"162545","playerCardId":"2326405","talentId":"4","level":"2","type":"1","fragmentNum":"36","gemstoneId":null,"createTime":"2021-11-12 01:05:55"},"2":{"id":"56211","playerId":"162545","playerCardId":"2326405","talentId":"2","level":"2","type":"1","fragmentNum":"27","gemstoneId":null,"createTime":"2021-11-12 01:05:40"},"9":{"id":"56218","playerId":"162545","playerCardId":"2326405","talentId":"9","level":"1","type":"2","fragmentNum":"200","gemstoneId":"285007","createTime":"2021-11-12 01:06:31"},"7":{"id":"56216","playerId":"162545","playerCardId":"2326405","talentId":"7","level":"2","type":"1","fragmentNum":"51","gemstoneId":null,"createTime":"2021-11-12 01:06:19"},"3":{"id":"56212","playerId":"162545","playerCardId":"2326405","talentId":"3","level":"1","type":"2","fragmentNum":"50","gemstoneId":"280206","createTime":"2021-11-12 01:05:49"},"17":{"id":"56475","playerId":"162545","playerCardId":"2326405","talentId":"17","level":"4","type":"1","fragmentNum":"243","gemstoneId":null,"createTime":"2021-11-13 23:33:52"}},"bookLevel":[],"equippedHouseCatGene":[],"playerPetId":"4535414","hp":18186,"attack":6177,"defence":485,"critRate":9259,"critDamage":8530,"attackRate":9947},{"id":"2814326","playerId":"162545","cardId":"200412","level":"120","exp":"2075300","breakLevel":"5","vigour":"100","skill":{"10823":{"level":41},"10824":{"level":41},"90412":{"level":1}},"businessSkill":[],"favorability":"1829","favorabilityLevel":"5","createTime":"2024-06-11 22:42:21","cardName":null,"defaultSkinId":"254121","marryTime":null,"isArtifactUnlock":"1","lunaTowerHp":"1.0000","lunaTowerEnergy":"0.0000","pets":{"1":{"petId":"210040","level":"30","breakLevel":"18","character":"1","attr":[{"type":"1","num":"70","quality":"5"},{"type":"1","num":"70","quality":"5"},{"type":"1","num":"70","quality":"5"},{"type":"6","num":"600","quality":"5"}],"isEvolution":"1","playerPetId":"276073"}},"artifactTalent":{"8":{"id":"79065","playerId":"162545","playerCardId":"2814326","talentId":"8","level":"3","type":"1","fragmentNum":"87","gemstoneId":null,"createTime":"2024-06-21 00:48:06"},"1":{"id":"79030","playerId":"162545","playerCardId":"2814326","talentId":"1","level":"2","type":"1","fragmentNum":"21","gemstoneId":null,"createTime":"2024-06-20 13:22:50"},"5":{"id":"79062","playerId":"162545","playerCardId":"2814326","talentId":"5","level":"2","type":"1","fragmentNum":"42","gemstoneId":null,"createTime":"2024-06-21 00:47:56"},"16":{"id":"79144","playerId":"162545","playerCardId":"2814326","talentId":"16","level":"4","type":"1","fragmentNum":"216","gemstoneId":null,"createTime":"2024-06-23 02:03:54"},"12":{"id":"79113","playerId":"162545","playerCardId":"2814326","talentId":"12","level":"3","type":"1","fragmentNum":"105","gemstoneId":null,"createTime":"2024-06-21 21:11:55"},"6":{"id":"79063","playerId":"162545","playerCardId":"2814326","talentId":"6","level":"1","type":"2","fragmentNum":"100","gemstoneId":"282206","createTime":"2024-06-21 00:47:59"},"15":{"id":"79143","playerId":"162545","playerCardId":"2814326","talentId":"15","level":"4","type":"1","fragmentNum":"186","gemstoneId":null,"createTime":"2024-06-23 02:03:51"},"14":{"id":"79142","playerId":"162545","playerCardId":"2814326","talentId":"14","level":"1","type":"2","fragmentNum":"400","gemstoneId":"284005","createTime":"2024-06-23 02:03:48"},"13":{"id":"79114","playerId":"162545","playerCardId":"2814326","talentId":"13","level":"3","type":"1","fragmentNum":"120","gemstoneId":null,"createTime":"2024-06-21 21:12:10"},"18":{"id":"79168","playerId":"162545","playerCardId":"2814326","talentId":"18","level":"1","type":"2","fragmentNum":"800","gemstoneId":"283106","createTime":"2024-06-23 20:20:39"},"4":{"id":"79061","playerId":"162545","playerCardId":"2814326","talentId":"4","level":"2","type":"1","fragmentNum":"36","gemstoneId":null,"createTime":"2024-06-21 00:47:53"},"2":{"id":"79031","playerId":"162545","playerCardId":"2814326","talentId":"2","level":"2","type":"1","fragmentNum":"27","gemstoneId":null,"createTime":"2024-06-20 13:22:52"},"9":{"id":"79066","playerId":"162545","playerCardId":"2814326","talentId":"9","level":"1","type":"2","fragmentNum":"200","gemstoneId":"280206","createTime":"2024-06-21 00:48:13"},"7":{"id":"79064","playerId":"162545","playerCardId":"2814326","talentId":"7","level":"2","type":"1","fragmentNum":"51","gemstoneId":null,"createTime":"2024-06-21 00:48:03"},"3":{"id":"79060","playerId":"162545","playerCardId":"2814326","talentId":"3","level":"1","type":"2","fragmentNum":"50","gemstoneId":"285007","createTime":"2024-06-21 00:47:37"},"17":{"id":"79145","playerId":"162545","playerCardId":"2814326","talentId":"17","level":"4","type":"1","fragmentNum":"243","gemstoneId":null,"createTime":"2024-06-23 02:04:23"}},"bookLevel":[],"equippedHouseCatGene":[],"playerPetId":"276073","attack":7480,"attackRate":15855,"defence":533,"hp":12125,"critRate":11683,"critDamage":16606},{"id":"2593113","playerId":"162545","cardId":"200285","level":"120","exp":"2117198","breakLevel":"5","vigour":"100","skill":{"10569":{"level":41},"10570":{"level":41},"90285":{"level":1}},"businessSkill":[],"favorability":"2650","favorabilityLevel":"6","createTime":"2022-07-13 13:00:41","cardName":null,"defaultSkinId":"252850","marryTime":"1665687040","isArtifactUnlock":"1","lunaTowerHp":"1.0000","lunaTowerEnergy":"0.0000","pets":{"1":{"petId":"210059","level":"30","breakLevel":"17","character":"1","attr":[{"type":"1","num":"60","quality":"5"},{"type":"1","num":"60","quality":"5"},{"type":"1","num":"60","quality":"5"},{"type":"6","num":"350","quality":"5"}],"isEvolution":"1","playerPetId":"4582526"}},"artifactTalent":{"8":{"id":"62989","playerId":"162545","playerCardId":"2593113","talentId":"8","level":"3","type":"1","fragmentNum":"87","gemstoneId":null,"createTime":"2022-07-26 16:20:37"},"1":{"id":"62982","playerId":"162545","playerCardId":"2593113","talentId":"1","level":"2","type":"1","fragmentNum":"21","gemstoneId":null,"createTime":"2022-07-26 16:20:18"},"11":{"id":"62992","playerId":"162545","playerCardId":"2593113","talentId":"11","level":"3","type":"1","fragmentNum":"120","gemstoneId":null,"createTime":"2022-07-26 16:20:48"},"5":{"id":"62986","playerId":"162545","playerCardId":"2593113","talentId":"5","level":"2","type":"1","fragmentNum":"42","gemstoneId":null,"createTime":"2022-07-26 16:20:29"},"16":{"id":"63003","playerId":"162545","playerCardId":"2593113","talentId":"16","level":"4","type":"1","fragmentNum":"216","gemstoneId":null,"createTime":"2022-07-26 18:19:16"},"12":{"id":"63041","playerId":"162545","playerCardId":"2593113","talentId":"12","level":"2","type":"1","fragmentNum":"132","gemstoneId":null,"createTime":"2022-07-27 11:58:14"},"6":{"id":"62987","playerId":"162545","playerCardId":"2593113","talentId":"6","level":"1","type":"2","fragmentNum":"100","gemstoneId":"282106","createTime":"2022-07-26 16:20:31"},"15":{"id":"62994","playerId":"162545","playerCardId":"2593113","talentId":"15","level":"4","type":"1","fragmentNum":"186","gemstoneId":null,"createTime":"2022-07-26 16:22:15"},"14":{"id":"62993","playerId":"162545","playerCardId":"2593113","talentId":"14","level":"1","type":"2","fragmentNum":"400","gemstoneId":"284106","createTime":"2022-07-26 16:22:00"},"10":{"id":"62991","playerId":"162545","playerCardId":"2593113","talentId":"10","level":"3","type":"1","fragmentNum":"105","gemstoneId":null,"createTime":"2022-07-26 16:20:43"},"4":{"id":"62985","playerId":"162545","playerCardId":"2593113","talentId":"4","level":"2","type":"1","fragmentNum":"36","gemstoneId":null,"createTime":"2022-07-26 16:20:27"},"2":{"id":"62983","playerId":"162545","playerCardId":"2593113","talentId":"2","level":"2","type":"1","fragmentNum":"27","gemstoneId":null,"createTime":"2022-07-26 16:20:22"},"9":{"id":"62990","playerId":"162545","playerCardId":"2593113","talentId":"9","level":"1","type":"2","fragmentNum":"200","gemstoneId":"280106","createTime":"2022-07-26 16:20:40"},"7":{"id":"62988","playerId":"162545","playerCardId":"2593113","talentId":"7","level":"2","type":"1","fragmentNum":"51","gemstoneId":null,"createTime":"2022-07-26 16:20:33"},"3":{"id":"62984","playerId":"162545","playerCardId":"2593113","talentId":"3","level":"1","type":"2","fragmentNum":"50","gemstoneId":"283106","createTime":"2022-07-26 16:20:24"},"17":{"id":"63004","playerId":"162545","playerCardId":"2593113","talentId":"17","level":"4","type":"1","fragmentNum":"243","gemstoneId":null,"createTime":"2022-07-26 18:19:21"},"18":{"id":"63005","playerId":"162545","playerCardId":"2593113","talentId":"18","level":"1","type":"2","fragmentNum":"800","gemstoneId":"283206","createTime":"2022-07-26 18:22:09"}},"bookLevel":[],"equippedHouseCatGene":[],"playerPetId":"4582526","attack":7853,"attackRate":12506,"defence":323,"hp":12898,"critRate":16442,"critDamage":15191},{"id":"1751961","playerId":"162545","cardId":"200099","level":"116","exp":"1843504","breakLevel":"5","vigour":"100","skill":{"10197":{"level":39},"10198":{"level":39}},"businessSkill":[],"favorability":"2650","favorabilityLevel":"6","createTime":"2019-06-29 05:20:52","cardName":null,"defaultSkinId":"250993","marryTime":"1609823887","isArtifactUnlock":"1","lunaTowerHp":"1.0000","lunaTowerEnergy":"0.0000","pets":{"1":{"petId":"210025","level":"30","breakLevel":"13","character":"3","attr":[{"type":"3","num":"595","quality":"5"},{"type":"3","num":"595","quality":"5"},{"type":"3","num":"595","quality":"5"},{"type":"3","num":"595","quality":"5"}],"isEvolution":"1","playerPetId":"519308"}},"artifactTalent":{"8":{"id":"46188","playerId":"162545","playerCardId":"1751961","talentId":"8","level":"3","type":"1","fragmentNum":"87","gemstoneId":null,"createTime":"2021-02-17 20:42:25"},"1":{"id":"40120","playerId":"162545","playerCardId":"1751961","talentId":"1","level":"2","type":"1","fragmentNum":"21","gemstoneId":null,"createTime":"2020-09-14 05:16:03"},"11":{"id":"54701","playerId":"162545","playerCardId":"1751961","talentId":"11","level":"3","type":"1","fragmentNum":"120","gemstoneId":null,"createTime":"2021-09-28 18:29:25"},"5":{"id":"40381","playerId":"162545","playerCardId":"1751961","talentId":"5","level":"2","type":"1","fragmentNum":"42","gemstoneId":null,"createTime":"2020-09-15 21:33:38"},"6":{"id":"40506","playerId":"162545","playerCardId":"1751961","talentId":"6","level":"1","type":"2","fragmentNum":"100","gemstoneId":"280104","createTime":"2020-09-17 04:37:17"},"15":{"id":"54746","playerId":"162545","playerCardId":"1751961","talentId":"15","level":"1","type":"1","fragmentNum":"45","gemstoneId":null,"createTime":"2021-09-29 19:26:38"},"14":{"id":"54702","playerId":"162545","playerCardId":"1751961","talentId":"14","level":"1","type":"2","fragmentNum":"400","gemstoneId":"283205","createTime":"2021-09-28 18:30:36"},"10":{"id":"46190","playerId":"162545","playerCardId":"1751961","talentId":"10","level":"3","type":"1","fragmentNum":"105","gemstoneId":null,"createTime":"2021-02-17 20:43:10"},"4":{"id":"40380","playerId":"162545","playerCardId":"1751961","talentId":"4","level":"2","type":"1","fragmentNum":"36","gemstoneId":null,"createTime":"2020-09-15 21:30:34"},"2":{"id":"40121","playerId":"162545","playerCardId":"1751961","talentId":"2","level":"2","type":"1","fragmentNum":"27","gemstoneId":null,"createTime":"2020-09-14 05:16:07"},"9":{"id":"46189","playerId":"162545","playerCardId":"1751961","talentId":"9","level":"1","type":"2","fragmentNum":"200","gemstoneId":282105,"createTime":"2021-02-17 20:43:02"},"7":{"id":"46187","playerId":"162545","playerCardId":"1751961","talentId":"7","level":"2","type":"1","fragmentNum":"51","gemstoneId":null,"createTime":"2021-02-17 20:42:20"},"3":{"id":"40339","playerId":"162545","playerCardId":"1751961","talentId":"3","level":"1","type":"2","fragmentNum":"50","gemstoneId":"285207","createTime":"2020-09-15 12:33:28"}},"bookLevel":[],"equippedHouseCatGene":[],"playerPetId":"519308","hp":31526,"attack":4125,"defence":540,"critRate":6272,"critDamage":5008,"attackRate":8077},{"id":"2421120","playerId":"162545","cardId":"200268","level":"100","exp":"1157454","breakLevel":"3","vigour":"100","skill":{"10535":{"level":34},"10536":{"level":34},"90268":{"level":1}},"businessSkill":[],"favorability":"2650","favorabilityLevel":"6","createTime":"2021-08-07 15:41:40","cardName":null,"defaultSkinId":"252680","marryTime":"1671625703","isArtifactUnlock":"1","lunaTowerHp":"1.0000","lunaTowerEnergy":"0.0000","pets":{"1":{"petId":"210040","level":"30","breakLevel":"14","character":"6","attr":[{"type":"6","num":"600","quality":"5"},{"type":"6","num":"600","quality":"5"},{"type":"6","num":"600","quality":"5"},{"type":"6","num":"600","quality":"5"}],"isEvolution":"1","playerPetId":"7519432"}},"artifactTalent":{"8":{"id":"57610","playerId":"162545","playerCardId":"2421120","talentId":"8","level":"3","type":"1","fragmentNum":"87","gemstoneId":null,"createTime":"2021-12-22 22:22:19"},"1":{"id":"57568","playerId":"162545","playerCardId":"2421120","talentId":"1","level":"2","type":"1","fragmentNum":"21","gemstoneId":null,"createTime":"2021-12-22 04:48:18"},"11":{"id":"57671","playerId":"162545","playerCardId":"2421120","talentId":"11","level":"3","type":"1","fragmentNum":"120","gemstoneId":null,"createTime":"2021-12-25 14:52:58"},"5":{"id":"57572","playerId":"162545","playerCardId":"2421120","talentId":"5","level":"2","type":"1","fragmentNum":"42","gemstoneId":null,"createTime":"2021-12-22 04:48:29"},"16":{"id":"67602","playerId":"162545","playerCardId":"2421120","talentId":"16","level":"4","type":"1","fragmentNum":"216","gemstoneId":null,"createTime":"2022-12-14 05:50:57"},"6":{"id":"57573","playerId":"162545","playerCardId":"2421120","talentId":"6","level":"1","type":"2","fragmentNum":"100","gemstoneId":"282106","createTime":"2021-12-22 04:48:31"},"15":{"id":"67601","playerId":"162545","playerCardId":"2421120","talentId":"15","level":"4","type":"1","fragmentNum":"186","gemstoneId":null,"createTime":"2022-12-14 05:50:44"},"14":{"id":"57672","playerId":"162545","playerCardId":"2421120","talentId":"14","level":"1","type":"2","fragmentNum":"400","gemstoneId":"284007","createTime":"2021-12-25 14:54:02"},"10":{"id":"57670","playerId":"162545","playerCardId":"2421120","talentId":"10","level":"3","type":"1","fragmentNum":"105","gemstoneId":null,"createTime":"2021-12-25 14:52:55"},"18":{"id":"67873","playerId":"162545","playerCardId":"2421120","talentId":"18","level":"1","type":"2","fragmentNum":"800","gemstoneId":"283007","createTime":"2022-12-16 21:34:57"},"4":{"id":"57571","playerId":"162545","playerCardId":"2421120","talentId":"4","level":"2","type":"1","fragmentNum":"36","gemstoneId":null,"createTime":"2021-12-22 04:48:26"},"2":{"id":"57569","playerId":"162545","playerCardId":"2421120","talentId":"2","level":"2","type":"1","fragmentNum":"27","gemstoneId":null,"createTime":"2021-12-22 04:48:20"},"9":{"id":"57669","playerId":"162545","playerCardId":"2421120","talentId":"9","level":"1","type":"2","fragmentNum":"200","gemstoneId":"280206","createTime":"2021-12-25 14:52:28"},"7":{"id":"57574","playerId":"162545","playerCardId":"2421120","talentId":"7","level":"2","type":"1","fragmentNum":"51","gemstoneId":null,"createTime":"2021-12-22 04:48:35"},"3":{"id":"57570","playerId":"162545","playerCardId":"2421120","talentId":"3","level":"1","type":"2","fragmentNum":"50","gemstoneId":"283006","createTime":"2021-12-22 04:48:23"},"17":{"id":"67751","playerId":"162545","playerCardId":"2421120","talentId":"17","level":"4","type":"1","fragmentNum":"243","gemstoneId":null,"createTime":"2022-12-15 16:20:48"}},"bookLevel":[],"equippedHouseCatGene":[],"playerPetId":"7519432","attackRate":27623,"attack":2589,"defence":468,"hp":9577,"critRate":10948,"critDamage":10211}],"team3":[{"id":"2716595","playerId":"162545","cardId":"200346","level":"120","exp":"2076724","breakLevel":"5","vigour":"100","skill":{"10691":{"level":41},"10692":{"level":41},"90346":{"level":1}},"businessSkill":[],"favorability":"2650","favorabilityLevel":"6","createTime":"2023-05-01 16:29:44","cardName":null,"defaultSkinId":"253460","marryTime":"1700933786","isArtifactUnlock":"1","lunaTowerHp":"1.0000","lunaTowerEnergy":"0.0000","pets":{"1":{"petId":"210060","level":"30","breakLevel":"20","character":"1","attr":[{"type":"1","num":"70","quality":"5"},{"type":"1","num":"70","quality":"5"},{"type":"1","num":"70","quality":"5"},{"type":"6","num":"600","quality":"5"}],"isEvolution":"1","playerPetId":"1847828"}},"artifactTalent":{"8":{"id":"70590","playerId":"162545","playerCardId":"2716595","talentId":"8","level":"3","type":"1","fragmentNum":"87","gemstoneId":null,"createTime":"2023-05-01 16:49:53"},"1":{"id":"70583","playerId":"162545","playerCardId":"2716595","talentId":"1","level":"2","type":"1","fragmentNum":"21","gemstoneId":null,"createTime":"2023-05-01 16:49:34"},"5":{"id":"70587","playerId":"162545","playerCardId":"2716595","talentId":"5","level":"2","type":"1","fragmentNum":"42","gemstoneId":null,"createTime":"2023-05-01 16:49:45"},"16":{"id":"70596","playerId":"162545","playerCardId":"2716595","talentId":"16","level":"4","type":"1","fragmentNum":"216","gemstoneId":null,"createTime":"2023-05-01 16:50:19"},"12":{"id":"70592","playerId":"162545","playerCardId":"2716595","talentId":"12","level":"3","type":"1","fragmentNum":"105","gemstoneId":null,"createTime":"2023-05-01 16:50:05"},"6":{"id":"70588","playerId":"162545","playerCardId":"2716595","talentId":"6","level":"1","type":"2","fragmentNum":"100","gemstoneId":"282106","createTime":"2023-05-01 16:49:47"},"15":{"id":"70595","playerId":"162545","playerCardId":"2716595","talentId":"15","level":"4","type":"1","fragmentNum":"186","gemstoneId":null,"createTime":"2023-05-01 16:50:14"},"14":{"id":"70594","playerId":"162545","playerCardId":"2716595","talentId":"14","level":"1","type":"2","fragmentNum":"400","gemstoneId":"284107","createTime":"2023-05-01 16:50:11"},"13":{"id":"70593","playerId":"162545","playerCardId":"2716595","talentId":"13","level":"3","type":"1","fragmentNum":"120","gemstoneId":null,"createTime":"2023-05-01 16:50:08"},"18":{"id":"70786","playerId":"162545","playerCardId":"2716595","talentId":"18","level":"1","type":"2","fragmentNum":"800","gemstoneId":"283207","createTime":"2023-05-10 12:03:11"},"4":{"id":"70586","playerId":"162545","playerCardId":"2716595","talentId":"4","level":"2","type":"1","fragmentNum":"36","gemstoneId":null,"createTime":"2023-05-01 16:49:43"},"2":{"id":"70584","playerId":"162545","playerCardId":"2716595","talentId":"2","level":"2","type":"1","fragmentNum":"27","gemstoneId":null,"createTime":"2023-05-01 16:49:38"},"9":{"id":"70591","playerId":"162545","playerCardId":"2716595","talentId":"9","level":"1","type":"2","fragmentNum":"200","gemstoneId":"280107","createTime":"2023-05-01 16:49:56"},"7":{"id":"70589","playerId":"162545","playerCardId":"2716595","talentId":"7","level":"2","type":"1","fragmentNum":"51","gemstoneId":null,"createTime":"2023-05-01 16:49:51"},"3":{"id":"70585","playerId":"162545","playerCardId":"2716595","talentId":"3","level":"1","type":"2","fragmentNum":"50","gemstoneId":"283206","createTime":"2023-05-01 16:49:40"},"17":{"id":"70600","playerId":"162545","playerCardId":"2716595","talentId":"17","level":"4","type":"1","fragmentNum":"243","gemstoneId":null,"createTime":"2023-05-01 18:30:19"}},"bookLevel":[],"equippedHouseCatGene":[],"playerPetId":"1847828","attack":8371,"attackRate":15624,"defence":603,"hp":14095,"critRate":12844,"critDamage":17241},{"id":"2174136","playerId":"162545","cardId":"200115","level":"113","exp":"1697674","breakLevel":"5","vigour":"100","skill":{"10229":{"level":38},"10230":{"level":38},"90115":{"level":1}},"businessSkill":[],"favorability":"2650","favorabilityLevel":"6","createTime":"2020-06-27 17:10:19","cardName":null,"defaultSkinId":"251150","marryTime":"1596333442","isArtifactUnlock":"1","lunaTowerHp":"1.0000","lunaTowerEnergy":"0.0000","pets":{"1":{"petId":"210054","level":"30","breakLevel":"10","character":"3","attr":[{"type":"1","num":"60","quality":"5"},{"type":"3","num":"595","quality":"5"},{"type":"1","num":"60","quality":"5"},{"type":"3","num":"595","quality":"5"}],"isEvolution":"1","playerPetId":"65715"}},"artifactTalent":{"1":{"id":"35925","playerId":"162545","playerCardId":"2174136","talentId":"1","level":"2","type":"1","fragmentNum":"21","gemstoneId":null,"createTime":"2020-07-04 13:07:21"},"11":{"id":"62473","playerId":"162545","playerCardId":"2174136","talentId":"11","level":"3","type":"1","fragmentNum":"219","gemstoneId":null,"createTime":"2022-07-17 21:47:03"},"5":{"id":"35929","playerId":"162545","playerCardId":"2174136","talentId":"5","level":"2","type":"1","fragmentNum":"42","gemstoneId":null,"createTime":"2020-07-04 13:07:44"},"16":{"id":"36487","playerId":"162545","playerCardId":"2174136","talentId":"16","level":"4","type":"1","fragmentNum":"216","gemstoneId":null,"createTime":"2020-07-05 12:46:38"},"12":{"id":"35934","playerId":"162545","playerCardId":"2174136","talentId":"12","level":"3","type":"1","fragmentNum":"105","gemstoneId":null,"createTime":"2020-07-04 13:10:22"},"6":{"id":"35930","playerId":"162545","playerCardId":"2174136","talentId":"6","level":"1","type":"2","fragmentNum":"100","gemstoneId":"282005","createTime":"2020-07-04 13:07:52"},"15":{"id":"36486","playerId":"162545","playerCardId":"2174136","talentId":"15","level":"4","type":"1","fragmentNum":"186","gemstoneId":null,"createTime":"2020-07-05 12:46:33"},"14":{"id":"36485","playerId":"162545","playerCardId":"2174136","talentId":"14","level":"1","type":"2","fragmentNum":"400","gemstoneId":"284105","createTime":"2020-07-05 12:46:29"},"13":{"id":"35935","playerId":"162545","playerCardId":"2174136","talentId":"13","level":"3","type":"1","fragmentNum":"120","gemstoneId":null,"createTime":"2020-07-04 13:10:25"},"10":{"id":"62472","playerId":"162545","playerCardId":"2174136","talentId":"10","level":"3","type":"1","fragmentNum":"201","gemstoneId":null,"createTime":"2022-07-17 21:46:39"},"4":{"id":"35928","playerId":"162545","playerCardId":"2174136","talentId":"4","level":"2","type":"1","fragmentNum":"36","gemstoneId":null,"createTime":"2020-07-04 13:07:37"},"2":{"id":"35926","playerId":"162545","playerCardId":"2174136","talentId":"2","level":"2","type":"1","fragmentNum":"27","gemstoneId":null,"createTime":"2020-07-04 13:07:24"},"9":{"id":"35933","playerId":"162545","playerCardId":"2174136","talentId":"9","level":"1","type":"2","fragmentNum":"200","gemstoneId":"280104","createTime":"2020-07-04 13:10:16"},"7":{"id":"35931","playerId":"162545","playerCardId":"2174136","talentId":"7","level":"2","type":"1","fragmentNum":"51","gemstoneId":null,"createTime":"2020-07-04 13:07:55"},"3":{"id":"35927","playerId":"162545","playerCardId":"2174136","talentId":"3","level":"1","type":"2","fragmentNum":"50","gemstoneId":"283102","createTime":"2020-07-04 13:07:32"},"8":{"id":"35932","playerId":"162545","playerCardId":"2174136","talentId":"8","level":"3","type":"1","fragmentNum":"87","gemstoneId":null,"createTime":"2020-07-04 13:07:58"},"17":{"id":"36709","playerId":"162545","playerCardId":"2174136","talentId":"17","level":"4","type":"1","fragmentNum":"243","gemstoneId":null,"createTime":"2020-07-06 17:49:12"},"18":{"id":"36808","playerId":"162545","playerCardId":"2174136","talentId":"18","level":"1","type":"2","fragmentNum":"800","gemstoneId":"283203","createTime":"2020-07-07 17:31:15"}},"bookLevel":[],"equippedHouseCatGene":[],"playerPetId":"65715","attack":4950,"hp":17897,"defence":264,"critRate":16472,"critDamage":12682,"attackRate":13338},{"id":"2690678","playerId":"162545","cardId":"200324","level":"90","exp":"792800","breakLevel":"2","vigour":"100","skill":{"10647":{"level":31},"10648":{"level":31},"90324":{"level":1}},"businessSkill":[],"favorability":"2650","favorabilityLevel":"6","createTime":"2023-02-22 00:23:18","cardName":null,"defaultSkinId":"253240","marryTime":"1714232996","isArtifactUnlock":"1","lunaTowerHp":"1.0000","lunaTowerEnergy":"0.0000","artifactTalent":{"8":{"id":"77776","playerId":"162545","playerCardId":"2690678","talentId":"8","level":"3","type":"1","fragmentNum":"87","gemstoneId":null,"createTime":"2024-04-02 13:39:20"},"1":{"id":"77769","playerId":"162545","playerCardId":"2690678","talentId":"1","level":"2","type":"1","fragmentNum":"21","gemstoneId":null,"createTime":"2024-04-02 13:39:02"},"11":{"id":"77794","playerId":"162545","playerCardId":"2690678","talentId":"11","level":"3","type":"1","fragmentNum":"120","gemstoneId":null,"createTime":"2024-04-03 05:00:12"},"5":{"id":"77773","playerId":"162545","playerCardId":"2690678","talentId":"5","level":"2","type":"1","fragmentNum":"42","gemstoneId":null,"createTime":"2024-04-02 13:39:12"},"16":{"id":"77812","playerId":"162545","playerCardId":"2690678","talentId":"16","level":"4","type":"1","fragmentNum":"216","gemstoneId":null,"createTime":"2024-04-03 14:57:53"},"6":{"id":"77774","playerId":"162545","playerCardId":"2690678","talentId":"6","level":"1","type":"2","fragmentNum":"100","gemstoneId":"282206","createTime":"2024-04-02 13:39:15"},"15":{"id":"77796","playerId":"162545","playerCardId":"2690678","talentId":"15","level":"4","type":"1","fragmentNum":"186","gemstoneId":null,"createTime":"2024-04-03 05:27:44"},"14":{"id":"77795","playerId":"162545","playerCardId":"2690678","talentId":"14","level":"1","type":"2","fragmentNum":"400","gemstoneId":"284006","createTime":"2024-04-03 05:27:34"},"10":{"id":"77793","playerId":"162545","playerCardId":"2690678","talentId":"10","level":"3","type":"1","fragmentNum":"105","gemstoneId":null,"createTime":"2024-04-03 05:00:07"},"18":{"id":"77845","playerId":"162545","playerCardId":"2690678","talentId":"18","level":"1","type":"2","fragmentNum":"800","gemstoneId":"283206","createTime":"2024-04-04 20:42:21"},"4":{"id":"77772","playerId":"162545","playerCardId":"2690678","talentId":"4","level":"2","type":"1","fragmentNum":"36","gemstoneId":null,"createTime":"2024-04-02 13:39:10"},"2":{"id":"77770","playerId":"162545","playerCardId":"2690678","talentId":"2","level":"2","type":"1","fragmentNum":"27","gemstoneId":null,"createTime":"2024-04-02 13:39:04"},"9":{"id":"77777","playerId":"162545","playerCardId":"2690678","talentId":"9","level":"1","type":"2","fragmentNum":"200","gemstoneId":"280007","createTime":"2024-04-02 13:39:29"},"7":{"id":"77775","playerId":"162545","playerCardId":"2690678","talentId":"7","level":"2","type":"1","fragmentNum":"51","gemstoneId":null,"createTime":"2024-04-02 13:39:18"},"3":{"id":"77771","playerId":"162545","playerCardId":"2690678","talentId":"3","level":"1","type":"2","fragmentNum":"50","gemstoneId":"283006","createTime":"2024-04-02 13:39:07"},"17":{"id":"77837","playerId":"162545","playerCardId":"2690678","talentId":"17","level":"4","type":"1","fragmentNum":"243","gemstoneId":null,"createTime":"2024-04-04 12:04:24"}},"bookLevel":[],"equippedHouseCatGene":[],"attack":1780,"defence":398,"hp":6643,"critRate":9924,"critDamage":9185,"attackRate":8749},{"id":"2772900","playerId":"162545","cardId":"200390","level":"90","exp":"814450","breakLevel":"2","vigour":"100","skill":{"10779":{"level":31},"10780":{"level":31},"90390":{"level":1}},"businessSkill":[],"favorability":"2650","favorabilityLevel":"6","createTime":"2023-12-09 01:08:28","cardName":null,"defaultSkinId":"253900","marryTime":"1704424283","isArtifactUnlock":"1","lunaTowerHp":"1.0000","lunaTowerEnergy":"0.0000","pets":{"1":{"petId":"210040","level":"30","breakLevel":"15","character":"6","attr":[{"type":"1","num":"70","quality":"5"},{"type":"6","num":"600","quality":"5"},{"type":"6","num":"600","quality":"5"},{"type":"6","num":"600","quality":"5"}],"isEvolution":"1","playerPetId":"7278884"}},"artifactTalent":{"8":{"id":"75600","playerId":"162545","playerCardId":"2772900","talentId":"8","level":"3","type":"1","fragmentNum":"87","gemstoneId":null,"createTime":"2023-12-10 11:18:20"},"1":{"id":"75593","playerId":"162545","playerCardId":"2772900","talentId":"1","level":"2","type":"1","fragmentNum":"21","gemstoneId":null,"createTime":"2023-12-10 11:17:45"},"5":{"id":"75597","playerId":"162545","playerCardId":"2772900","talentId":"5","level":"2","type":"1","fragmentNum":"42","gemstoneId":null,"createTime":"2023-12-10 11:18:03"},"16":{"id":"75641","playerId":"162545","playerCardId":"2772900","talentId":"16","level":"4","type":"1","fragmentNum":"216","gemstoneId":null,"createTime":"2023-12-11 01:59:35"},"12":{"id":"75637","playerId":"162545","playerCardId":"2772900","talentId":"12","level":"3","type":"1","fragmentNum":"105","gemstoneId":null,"createTime":"2023-12-11 01:55:06"},"6":{"id":"75598","playerId":"162545","playerCardId":"2772900","talentId":"6","level":"1","type":"2","fragmentNum":"100","gemstoneId":"282107","createTime":"2023-12-10 11:18:07"},"15":{"id":"75640","playerId":"162545","playerCardId":"2772900","talentId":"15","level":"4","type":"1","fragmentNum":"186","gemstoneId":null,"createTime":"2023-12-11 01:59:30"},"14":{"id":"75639","playerId":"162545","playerCardId":"2772900","talentId":"14","level":"1","type":"2","fragmentNum":"400","gemstoneId":"284207","createTime":"2023-12-11 01:59:26"},"13":{"id":"75638","playerId":"162545","playerCardId":"2772900","talentId":"13","level":"3","type":"1","fragmentNum":"120","gemstoneId":null,"createTime":"2023-12-11 01:55:09"},"18":{"id":"75643","playerId":"162545","playerCardId":"2772900","talentId":"18","level":"1","type":"2","fragmentNum":"800","gemstoneId":"283107","createTime":"2023-12-11 02:05:18"},"4":{"id":"75596","playerId":"162545","playerCardId":"2772900","talentId":"4","level":"2","type":"1","fragmentNum":"36","gemstoneId":null,"createTime":"2023-12-10 11:17:58"},"2":{"id":"75594","playerId":"162545","playerCardId":"2772900","talentId":"2","level":"2","type":"1","fragmentNum":"27","gemstoneId":null,"createTime":"2023-12-10 11:17:49"},"9":{"id":"75601","playerId":"162545","playerCardId":"2772900","talentId":"9","level":"1","type":"2","fragmentNum":"200","gemstoneId":"280007","createTime":"2023-12-10 11:18:25"},"7":{"id":"75599","playerId":"162545","playerCardId":"2772900","talentId":"7","level":"2","type":"1","fragmentNum":"51","gemstoneId":null,"createTime":"2023-12-10 11:18:13"},"3":{"id":"75595","playerId":"162545","playerCardId":"2772900","talentId":"3","level":"1","type":"2","fragmentNum":"50","gemstoneId":"285207","createTime":"2023-12-10 11:17:54"},"17":{"id":"75642","playerId":"162545","playerCardId":"2772900","talentId":"17","level":"4","type":"1","fragmentNum":"243","gemstoneId":null,"createTime":"2023-12-11 02:00:14"}},"bookLevel":[],"equippedHouseCatGene":[],"playerPetId":"7278884","attack":2578,"attackRate":24468,"defence":201,"hp":5233,"critRate":7613,"critDamage":13169},{"id":"2638084","playerId":"162545","cardId":"200274","level":"118","exp":"1972300","breakLevel":"5","vigour":"100","skill":{"10547":{"level":40},"10548":{"level":40},"90274":{"level":1}},"businessSkill":[],"favorability":"2650","favorabilityLevel":"5","createTime":"2022-10-22 21:21:17","cardName":null,"defaultSkinId":"252743","marryTime":null,"isArtifactUnlock":"1","lunaTowerHp":"1.0000","lunaTowerEnergy":"0.0000","pets":{"1":{"petId":"210018","level":"30","breakLevel":"12","character":"6","attr":[{"type":"6","num":"350","quality":"5"},{"type":"6","num":"350","quality":"5"},{"type":"6","num":"350","quality":"5"},{"type":"6","num":"350","quality":"5"}],"isEvolution":"1","playerPetId":"913691"}},"artifactTalent":{"8":{"id":"67220","playerId":"162545","playerCardId":"2638084","talentId":"8","level":"3","type":"1","fragmentNum":"87","gemstoneId":null,"createTime":"2022-12-05 13:04:07"},"1":{"id":"67213","playerId":"162545","playerCardId":"2638084","talentId":"1","level":"2","type":"1","fragmentNum":"21","gemstoneId":null,"createTime":"2022-12-05 13:02:06"},"16":{"id":"67226","playerId":"162545","playerCardId":"2638084","talentId":"16","level":"4","type":"1","fragmentNum":"216","gemstoneId":null,"createTime":"2022-12-05 13:08:20"},"6":{"id":"67218","playerId":"162545","playerCardId":"2638084","talentId":"6","level":"1","type":"2","fragmentNum":"100","gemstoneId":null,"createTime":"2022-12-05 13:02:58"},"13":{"id":"67223","playerId":"162545","playerCardId":"2638084","talentId":"13","level":"3","type":"1","fragmentNum":"120","gemstoneId":null,"createTime":"2022-12-05 13:05:44"},"15":{"id":"67225","playerId":"162545","playerCardId":"2638084","talentId":"15","level":"4","type":"1","fragmentNum":"186","gemstoneId":null,"createTime":"2022-12-05 13:08:05"},"9":{"id":"67221","playerId":"162545","playerCardId":"2638084","talentId":"9","level":"1","type":"2","fragmentNum":"200","gemstoneId":283106,"createTime":"2022-12-05 13:04:16"},"2":{"id":"67214","playerId":"162545","playerCardId":"2638084","talentId":"2","level":"2","type":"1","fragmentNum":"27","gemstoneId":null,"createTime":"2022-12-05 13:02:10"},"4":{"id":"67216","playerId":"162545","playerCardId":"2638084","talentId":"4","level":"2","type":"1","fragmentNum":"36","gemstoneId":null,"createTime":"2022-12-05 13:02:16"},"3":{"id":"67215","playerId":"162545","playerCardId":"2638084","talentId":"3","level":"1","type":"2","fragmentNum":"50","gemstoneId":280106,"createTime":"2022-12-05 13:02:12"},"17":{"id":"67227","playerId":"162545","playerCardId":"2638084","talentId":"17","level":"4","type":"1","fragmentNum":"243","gemstoneId":null,"createTime":"2022-12-05 13:09:35"},"5":{"id":"67217","playerId":"162545","playerCardId":"2638084","talentId":"5","level":"2","type":"1","fragmentNum":"42","gemstoneId":null,"createTime":"2022-12-05 13:02:19"},"12":{"id":"67222","playerId":"162545","playerCardId":"2638084","talentId":"12","level":"3","type":"1","fragmentNum":"105","gemstoneId":null,"createTime":"2022-12-05 13:04:37"},"14":{"id":"67224","playerId":"162545","playerCardId":"2638084","talentId":"14","level":"1","type":"2","fragmentNum":"400","gemstoneId":284105,"createTime":"2022-12-05 13:08:01"},"18":{"id":"67228","playerId":"162545","playerCardId":"2638084","talentId":"18","level":"1","type":"2","fragmentNum":"800","gemstoneId":"280007","createTime":"2022-12-05 13:12:32"},"7":{"id":"67219","playerId":"162545","playerCardId":"2638084","talentId":"7","level":"2","type":"1","fragmentNum":"51","gemstoneId":null,"createTime":"2022-12-05 13:03:03"}},"bookLevel":[],"equippedHouseCatGene":[],"playerPetId":"913691","attackRate":17704,"attack":1823,"defence":514,"hp":9267,"critRate":6732,"critDamage":12199}]},"timestamp":1725306414,"errcode":0,"errmsg":"","rand":"66d6162e886731725306414","sign":"2cc0adb02598130fa7b63552fa908b22"}